Metadata-Version: 2.1
Name: twarc-hashtags
Version: 0.0.4
Summary: A twarc plugin to extract hashtags from Twitter data
Home-page: https://github.com/docnow/twarc-hashtags
Author: Ed Summers
Author-email: ehs@pobox.com
License: UNKNOWN
Platform: UNKNOWN
Requires-Python: >=3.3
License-File: LICENSE
